urlops/__init__.py
urlops/exceptions.py
urlops/path.py
urlops/query.py
urlops/url.py
urlops-1.0.5.dist-info/LICENSE
urlops-1.0.5.dist-info/METADATA
urlops-1.0.5.dist-info/WHEEL
urlops-1.0.5.dist-info/top_level.txt
urlops-1.0.5.dist-info/RECORD
