Metadata-Version: 2.1
Name: urlops
Version: 1.0.5
Summary: Clean URL handling made easy
Author-email: Rahul Vishwakarma <rahulvv8878@gmail.com>
License: MIT
Project-URL: Homepage, https://github.com/RVV-karma/urlops
Project-URL: Documentation, https://github.com/RVV-karma/urlops#readme
Project-URL: Repository, https://github.com/RVV-karma/urlops.git
Project-URL: Bug Tracker, https://github.com/RVV-karma/urlops/issues
Classifier: Development Status :: 3 - Alpha
Classifier: Intended Audience :: Developers
Classifier: Programming Language :: Python :: 3
Classifier: Programming Language :: Python :: 3.8
Classifier: Programming Language :: Python :: 3.9
Classifier: Programming Language :: Python :: 3.10
Classifier: Programming Language :: Python :: 3.11
Classifier: Programming Language :: Python :: 3.12
Requires-Python: >=3.8
License-File: LICENSE
Provides-Extra: dev
Requires-Dist: pytest>=7.0; extra == "dev"
Requires-Dist: pytest-cov>=4.0; extra == "dev"
Requires-Dist: black>=23.0; extra == "dev"
Requires-Dist: ruff>=0.1; extra == "dev"
